LICENSE
MANIFEST.in
README.md
byteps.exp
byteps.lds
pre_setup.py
setup.cfg
setup.py
ucx.zip
zeromq-4.1.4.tar.gz
./pre_setup.py
3rdparty/ps-lite/.git
3rdparty/ps-lite/.gitignore
3rdparty/ps-lite/.travis.yml
3rdparty/ps-lite/CMakeLists.txt
3rdparty/ps-lite/LICENSE
3rdparty/ps-lite/Makefile
3rdparty/ps-lite/README.md
3rdparty/ps-lite/efa.md
3rdparty/ps-lite/.github/workflows/main.yml
3rdparty/ps-lite/cmake/ProtoBuf.cmake
3rdparty/ps-lite/cmake/External/zmq.cmake
3rdparty/ps-lite/cmake/Modules/FindZMQ.cmake
3rdparty/ps-lite/docs/Doxyfile
3rdparty/ps-lite/docs/Makefile
3rdparty/ps-lite/docs/api.md
3rdparty/ps-lite/docs/conf.py
3rdparty/ps-lite/docs/env.md
3rdparty/ps-lite/docs/get_started.md
3rdparty/ps-lite/docs/how_to.md
3rdparty/ps-lite/docs/index.md
3rdparty/ps-lite/docs/overview.md
3rdparty/ps-lite/docs/requirements.txt
3rdparty/ps-lite/docs/sphinx_util.py
3rdparty/ps-lite/docs/tutorials.md
3rdparty/ps-lite/include/dmlc/base.h
3rdparty/ps-lite/include/dmlc/logging.h
3rdparty/ps-lite/include/ps/base.h
3rdparty/ps-lite/include/ps/kv_app.h
3rdparty/ps-lite/include/ps/ps.h
3rdparty/ps-lite/include/ps/range.h
3rdparty/ps-lite/include/ps/sarray.h
3rdparty/ps-lite/include/ps/simple_app.h
3rdparty/ps-lite/include/ps/internal/assign_op.h
3rdparty/ps-lite/include/ps/internal/customer.h
3rdparty/ps-lite/include/ps/internal/env.h
3rdparty/ps-lite/include/ps/internal/message.h
3rdparty/ps-lite/include/ps/internal/parallel_kv_match.h
3rdparty/ps-lite/include/ps/internal/parallel_sort.h
3rdparty/ps-lite/include/ps/internal/postoffice.h
3rdparty/ps-lite/include/ps/internal/threadsafe_queue.h
3rdparty/ps-lite/include/ps/internal/utils.h
3rdparty/ps-lite/include/ps/internal/van.h
3rdparty/ps-lite/make/deps.mk
3rdparty/ps-lite/make/ps.mk
3rdparty/ps-lite/src/customer.cc
3rdparty/ps-lite/src/fabric_transport.h
3rdparty/ps-lite/src/fabric_utils.h
3rdparty/ps-lite/src/fabric_van.h
3rdparty/ps-lite/src/meta.h
3rdparty/ps-lite/src/network_utils.h
3rdparty/ps-lite/src/postoffice.cc
byted_byteps.egg-info/PKG-INFO
byted_byteps.egg-info/SOURCES.txt
byted_byteps.egg-info/dependency_links.txt
byted_byteps.egg-info/top_level.txt
byteps.egg-info/PKG-INFO
byteps.egg-info/SOURCES.txt
byteps.egg-info/dependency_links.txt
byteps.egg-info/top_level.txt
