Metadata-Version: 2.1
Name: byteps
Version: 0.2.5.post15
Summary: A high-performance cross-framework Parameter Server for Deep Learning
Home-page: https://github.com/bytedance/byteps
Author: Bytedance Inc.
Author-email: lab-hr@bytedance.com
License: Apache
Platform: UNKNOWN
Classifier: License :: OSI Approved :: Apache Software License
Classifier: Programming Language :: Python
Classifier: Programming Language :: Python :: 3
Classifier: Programming Language :: Python :: 3.6
Classifier: Programming Language :: Python :: Implementation :: CPython
Classifier: Programming Language :: Python :: Implementation :: PyPy
Classifier: Operating System :: POSIX :: Linux
Requires-Python: >=2.7.0
